CHANGES.rst
MANIFEST.in
README.rst
setup.cfg
setup.py
Products/__init__.py
Products.remember.egg-info/PKG-INFO
Products.remember.egg-info/SOURCES.txt
Products.remember.egg-info/dependency_links.txt
Products.remember.egg-info/entry_points.txt
Products.remember.egg-info/namespace_packages.txt
Products.remember.egg-info/not-zip-safe
Products.remember.egg-info/requires.txt
Products.remember.egg-info/top_level.txt
Products/remember/__init__.py
Products/remember/config.py
Products/remember/configure.zcml
Products/remember/interfaces.py
Products/remember/overrides.zcml
Products/remember/permissions.py
Products/remember/security.py
Products/remember/setuphandlers.py
Products/remember/testing.zcml
Products/remember/utilities.py
Products/remember/utils.py
Products/remember/Extensions/Install.py
Products/remember/Extensions/__init__.py
Products/remember/Extensions/migrations.py
Products/remember/Extensions/remove_cmfmember.py
Products/remember/Extensions/toolbox.py
Products/remember/Extensions/workflow.py
Products/remember/browser/__init__.py
Products/remember/browser/configlet.py
Products/remember/browser/configletform.pt
Products/remember/browser/configure.zcml
Products/remember/browser/usergroups_usersoverview.pt
Products/remember/browser/utils.py
Products/remember/browser/vocabularies.py
Products/remember/cmfmember/README.txt
Products/remember/cmfmember/__init__.py
Products/remember/cmfmember/config.py
Products/remember/cmfmember/migrator.py
Products/remember/cmfmember/monkey.py
Products/remember/content/__init__.py
Products/remember/content/groups.py
Products/remember/content/member.py
Products/remember/content/member_schema.py
Products/remember/content/password_hashers.py
Products/remember/content/rememberuserchanger.py
Products/remember/content/useridprovider.py
Products/remember/docs/tutorial/01-intro.stx
Products/remember/docs/tutorial/02-infrastructure-overview.stx
Products/remember/docs/tutorial/03-package-structure.stx
Products/remember/docs/tutorial/04-create-custom-content.stx
Products/remember/docs/tutorial/05-genericsetup.stx
Products/remember/docs/tutorial/06-installation-configuration.stx
Products/remember/docs/tutorial/07-nextsteps.stx
Products/remember/docs/tutorial/README.txt
Products/remember/docs/tutorial/image-06-create-site.png
Products/remember/docs/tutorial/image-06-profile.png
