Metadata-Version: 1.1
Name: Products.remember
Version: 1.9.3
Summary: A content-based implementation of Plone's default member infrastructure
Home-page: http://plone.org/products/remember
Author: Ken Manheimer
Author-email: Ken.Manheimer@gmail.com
License: GPL
Keywords: plone membrane membership content remember
Platform: UNKNOWN
Classifier: Framework :: Plone
Classifier: Framework :: Plone :: 4.1
Classifier: Framework :: Plone :: 4.2
Classifier: Framework :: Plone :: 4.3
Classifier: Environment :: Web Environment
Classifier: Programming Language :: Python
Classifier: Programming Language :: Python :: 2.6
Classifier: Programming Language :: Python :: 2.7
Classifier: Topic :: Software Development :: Libraries :: Python Modules
Classifier: Development Status :: 4 - Beta
Classifier: License :: OSI Approved :: GNU General Public License (GPL)
Classifier: Operating System :: OS Independent
Classifier: Topic :: Software Development :: Libraries :: Python Modules
Classifier: Intended Audience :: Other Audience
Classifier: Intended Audience :: System Administrators
Classifier: Intended Audience :: Developers
